README.md
setup.py
cselector/__init__.py
cselector/cselector.py
cselector.egg-info/PKG-INFO
cselector.egg-info/SOURCES.txt
cselector.egg-info/dependency_links.txt
cselector.egg-info/not-zip-safe
cselector.egg-info/top_level.txt