Metadata-Version: 2.1
Name: cselector
Version: 0.3.0
Summary: Console single/multi selector for python.
Home-page: https://github.com/aieater/python_console_selector
Author: Pegara, Inc.
Author-email: info@pegara.com
License: MIT
Keywords: console temrinal selector pick picker menu
Platform: UNKNOWN
Classifier: License :: OSI Approved :: MIT License
Classifier: Operating System :: OS Independent
Classifier: Programming Language :: Python :: 3
Classifier: Programming Language :: Python :: 3.4
Classifier: Programming Language :: Python :: 3.5
Classifier: Programming Language :: Python :: 3.6
Classifier: Programming Language :: Python :: 3.7
Classifier: Programming Language :: Python :: 3.8
